tonpay/__init__.py
tonpay/constants.py
tonpay/currency.py
tonpay/enums.py
tonpay/contracts/__init__.py
tonpay/contracts/invoice/__init__.py
tonpay/contracts/invoice/_code.py
tonpay/contracts/invoice/_contract.py
tonpay/contracts/invoice/_deeplink.py
tonpay/contracts/invoice/_invoice.py
tonpay/contracts/invoice/_messages.py
tonpay/contracts/invoice/_opcodes.py
tonpay/contracts/invoice/_types.py
tonpay/contracts/jetton_wallet/__init__.py
tonpay/contracts/jetton_wallet/_messages.py
tonpay/contracts/jetton_wallet/_opcodes.py
tonpay/contracts/store/__init__.py
tonpay/contracts/store/_code.py
tonpay/contracts/store/_contract.py
tonpay/contracts/store/_deeplink.py
tonpay/contracts/store/_messages.py
tonpay/contracts/store/_opcodes.py
tonpay/contracts/store/_store.py
tonpay/contracts/store/_types.py
tonpay/network/__init__.py
tonpay/network/_sender.py
tonpay/utils/__init__.py
tonpay/utils/_strings.py
tonpay/utils/deeplink/__init__.py
tonpay/utils/deeplink/_ton.py
tonpay/utils/ton_access/__init__.py
tonpay/utils/ton_access/_access.py
tonpay/utils/ton_access/_node.py
tonpay-0.1.2.dist-info/LICENSE
tonpay-0.1.2.dist-info/METADATA
tonpay-0.1.2.dist-info/WHEEL
tonpay-0.1.2.dist-info/top_level.txt
tonpay-0.1.2.dist-info/RECORD
