Metadata-Version: 2.1
Name: tonpay
Version: 0.1.2
Summary: SDK for crypto payment system Tonpay
Author-email: Arterialist <arterialist@thetonpay.app>
License: MIT License
Project-URL: Homepage, https://github.com/TheTonpay/tonpay-python-sdk
Project-URL: Bug Tracker, https://github.com/TheTonpay/tonpay-python-sdk/issues
Project-URL: Documentation, https://tonpay.gitbook.io/tonpay-sdk/
Project-URL: Technical Support, https://t.me/+zdOo27FJZgg0ZGUy
Project-URL: Website, https://thetonpay.app/
Project-URL: Merchant Portal, https://business.thetonpay.app/
Classifier: Programming Language :: Python :: 3
Classifier: License :: OSI Approved :: MIT License
Classifier: Operating System :: OS Independent
Requires-Python: >=3.9
License-File: LICENSE
